confy_cli/__init__.py
confy_cli/core/__init__.py
confy_cli/core/constants.py
confy_cli/main.py
confy_cli/settings.py
confy_cli/utils.py
confy_cli-0.1.4.dist-info/METADATA
confy_cli-0.1.4.dist-info/WHEEL
confy_cli-0.1.4.dist-info/entry_points.txt
confy_cli-0.1.4.dist-info/licenses/LICENSE
confy_cli-0.1.4.dist-info/RECORD
