Metadata-Version: 2.4
Name: confy-cli
Version: 0.1.4
Summary: CLI client for the Confy encrypted communication system
License-Expression: GPL-3.0-or-later
License-File: LICENSE
Author: Henrique Sebastião
Author-email: contato@henriquesebastiao.com
Requires-Python: >=3.13,<4.0
Classifier: Development Status :: 5 - Production/Stable
Classifier: Environment :: Console
Classifier: Intended Audience :: Telecommunications Industry
Classifier: Intended Audience :: Information Technology
Classifier: Intended Audience :: Developers
Classifier: Intended Audience :: End Users/Desktop
Classifier: License :: OSI Approved :: GNU General Public License v3 (GPLv3)
Classifier: Natural Language :: English
Classifier: Operating System :: Microsoft :: Windows
Classifier: Operating System :: MacOS
Classifier: Operating System :: Unix
Classifier: Programming Language :: Python :: 3.13
Classifier: Topic :: Communications :: Chat
Classifier: Topic :: Security :: Cryptography
Classifier: Topic :: Utilities
Requires-Dist: confy-addons (>=1.1.0,<2.0.0)
Requires-Dist: prompt-toolkit (>=3.0.52,<4.0.0)
Requires-Dist: pydantic-settings (>=2.11.0,<3.0.0)
Requires-Dist: typer (>=0.15.4,<0.16.0)
Requires-Dist: websockets (>=15.0.1,<16.0.0)
Project-URL: Bug Tracker, https://github.com/confy-security/cli/issues
Project-URL: Changelog, https://github.com/confy-security/cli/blob/main/CHANGELOG
Project-URL: Source, https://github.com/confy-security/cli
